Workbook

Sheet Summary
A1: Maritime Traffic Analytics - North Sea & English Channel
A2: Snapshot taken 2026-10-11 08:17 UTC. Source: live AIS feed (AISStream), cleaned by run_all.py.
A4: Metric | B4: Value | C4: Note
A5: Ships in the snapshot (after cleaning) | B5: 6877
A6: Under way, speed 0.5 kn or more (%) | B6: 0.168
A7: Idle: stationary but status says under way (%) | B7: 0.293
A8: At anchor (%) | B8: 0.101
A9: At berth / moored (%) | B9: 0.439
A10: Ships inside a port hub's radius | B10: 3233
A11: Ships waiting at anchor near a hub | B11: 275
A12: Dark-fleet flagged (%) | B12: 0.0795
A13: Vessel type unknown (%) | B13: 0.032
A14: With an IMO number (%) | B14: 0.265
A15: IMO passes checksum (%) | B15: 0.255
A16: Destination usable (%) | B16: 0.79
... A19: Median speed of moving ships (kn) | B19: 7.4
A20: Busiest hub (ships in radius) | B20: Rotterdam
A21: Hub with most ships waiting at anchor | B21: Rotterdam
A23: Live check from the Clean_Data sheet (formula, recalculates):
A24: Ships in Clean_Data | B24: =COUNTA(Clean_Data!A2:A6878)
A25: Share moving | B25: =COUNTIF(Clean_Data!K:K,"moving")/B24
A27: Sheets
A28: Hub_Congestion | B28: Ships waiting at anchor near each hub, with green/yellow/red levels (relative to the other hubs)
A29: Fleet_Mix | B29: Live pivot (COUNTIFS on Clean_Data): vessel type x status
A30: Flags / Routes | B30: Top flag states; most common departure -> destination voyages
A31: Data_Quality | B31: Every cleaning rule with the number of rows it touched, and field completeness
A32: Assumptions | B32: Blue cells are inputs with sources. Change one and Estimates recalculates
A33: Estimates | B33: Fuel, CO2 and cost of ships waiting at anchor: ESTIMATES, low / central / high
A34: Clean_Data | B34: The cleaned dataset

Sheet Hub_Congestion
A1: hub | B1: zone | C1: ships_in_radius | D1: at_anchor | E1: idle | F1: at_berth | G1: moving | H1: waiting_broad | I1: avg_speed_moving_kn | J1: pct_at_anchor | K1: level_waiting | L1: level_waiting_broad
A2: Rotterdam | B2: Benelux coast | C2: 1079 | D2: 71 | E2: 279 | F2: 644 | G2: 85 | H2: 350 | I2: 7.6 | J2: 6.6 | K2: red | L2: red
A3: Amsterdam | B3: Benelux coast | C3: 724 | D3: 66 | E3: 328 | F3: 258 | G3: 72 | H3: 394 | I3: 4.7 | J3: 9.1 | K3: red | L3: red
A4: Antwerp | B4: Benelux coast | C4: 378 | D4: 31 | E4: 85 | F4: 199 | G4: 63 | H4: 116 | I4: 6.6 | J4: 8.2 | K4: red | L4: red
A5: Le Havre | B5: Dover Strait & Channel | C5: 93 | D5: 22 | E5: 16 | F5: 30 | G5: 25 | H5: 38 | I5: 8.2 | J5: 23.7 | K5: red | L5: red
A6: IJmuiden | B6: Benelux coast | C6: 144 | D6: 14 | E6: 41 | F6: 82 | G6: 7 | H6: 55 | I6: 4.9 | J6: 9.7 | K6: red | L6: red
A7: Terneuzen | B7: Benelux coast | C7: 132 | D7: 10 | E7: 30 | F7: 70 | G7: 22 | H7: 40 | I7: 6.3 | J7: 7.6 | K7: red | L7: red
A8: Vlissingen | B8: Benelux coast | C8: 125 | D8: 10 | E8: 41 | F8: 62 | G8: 12 | H8: 51 | I8: 8 | J8: 8 | K8: red | L8: red
A9: Bremerhaven | B9: German Bight & Ems | C9: 104 | D9: 9 | E9: 21 | F9: 65 | G9: 9 | H9: 30 | I9: 6.5 | J9: 8.7 | K9: yellow | L9: yellow
A10: Emden | B10: German Bight & Ems | C10: 57 | D10: 8 | E10: 15 | F10: 26 | G10: 8 | H10: 23 | I10: 7.3 | J10: 14 | K10: yellow | L10: yellow
A11: Wilhelmshaven | B11: German Bight & Ems | C11: 66 | D11: 7 | E11: 14 | F11: 45 | G11: 0 | H11: 21 | J11: 10.6 | K11: yellow | L11: yellow
A12: Eemshaven | B12: German Bight & Ems | C12: 103 | D12: 6 | E12: 31 | F12: 60 | G12: 6 | H12: 37 | I12: 5.5 | J12: 5.8 | K12: yellow | L12: yellow
A13: Zeebrugge | B13: Benelux coast | C13: 57 | D13: 6 | E13: 8 | F13: 34 | G13: 9 | H13: 14 | I13: 9.8 | J13: 10.5 | K13: yellow | L13: yellow
A14: Felixstowe | B14: UK east coast & Thames | C14: 34 | D14: 6 | E14: 2 | F14: 21 | G14: 5 | H14: 8 | I14: 7.1 | J14: 17.6 | K14: yellow | L14: green
A15: Southampton | B15: Dover Strait & Channel | C15: 57 | D15: 5 | E15: 12 | F15: 31 | G15: 9 | H15: 17 | I15: 11.8 | J15: 8.8 | K15: green | L15: yellow
A16: Thames (London Gateway) | B16: UK east coast & Thames | C16: 49 | D16: 3 | E16: 8 | F16: 30 | G16: 8 | H16: 11 | I16: 8.2 | J16: 6.1 | K16: green | L16: green
A17: Immingham (Humber) | B17: UK east coast & Thames | C17: 23 | D17: 1 | E17: 3 | F17: 16 | G17: 3 | H17: 4 | I17: 8.2 | J17: 4.3 | K17: green | L17: green
A18: Dover | B18: Dover Strait & Channel | C18: 5 | D18: 0 | E18: 1 | F18: 0 | G18: 4 | H18: 1 | I18: 14.6 | J18: 0 | K18: green | L18: green
A19: Calais | B19: Dover Strait & Channel | C19: 3 | D19: 0 | E19: 0 | F19: 0 | G19: 3 | H19: 0 | I19: 4.6 | J19: 0 | K19: green | L19: green
A20: Dunkirk | B20: Dover Strait & Channel | C20: 0 | D20: 0 | E20: 0 | F20: 0 | G20: 0 | H20: 0 | K20: green | L20: green
A22: Levels are relative: the lowest third of hubs is green, the middle third yellow, the top third red. They are not an industry standard.

Sheet Fleet_Mix
A1: Vessel type x status (live COUNTIFS on Clean_Data)
A3: vessel_type | B3: at_anchor | C3: at_berth | D3: idle | E3: moving | F3: other | G3: total | H3: share
A4: other | B4: =COUNTIFS(Clean_Data!$D:$D,$A4,Clean_Data!$K:$K,B$3) | C4: =COUNTIFS(Clean_Data!$D:$D,$A4,Clean_Data!$K:$K,C$3) | D4: =COUNTIFS(Clean_Data!$D:$D,$A4,Clean_Data!$K:$K,D$3) | E4: =COUNTIFS(Clean_Data!$D:$D,$A4,Clean_Data!$K:$K,E$3) | F4: =COUNTIFS(Clean_Data!$D:$D,$A4,Clean_Data!$K:$K,F$3) | G4: =SUM(B4:F4) | H4: =G4/G$13
A5: cargo | B5: =COUNTIFS(Clean_Data!$D:$D,$A5,Clean_Data!$K:$K,B$3) | C5: =COUNTIFS(Clean_Data!$D:$D,$A5,Clean_Data!$K:$K,C$3) | D5: =COUNTIFS(Clean_Data!$D:$D,$A5,Clean_Data!$K:$K,D$3) | E5: =COUNTIFS(Clean_Data!$D:$D,$A5,Clean_Data!$K:$K,E$3) | F5: =COUNTIFS(Clean_Data!$D:$D,$A5,Clean_Data!$K:$K,F$3) | G5: =SUM(B5:F5) | H5: =G5/G$13
A6: passenger | B6: =COUNTIFS(Clean_Data!$D:$D,$A6,Clean_Data!$K:$K,B$3) | C6: =COUNTIFS(Clean_Data!$D:$D,$A6,Clean_Data!$K:$K,C$3) | D6: =COUNTIFS(Clean_Data!$D:$D,$A6,Clean_Data!$K:$K,D$3) | E6: =COUNTIFS(Clean_Data!$D:$D,$A6,Clean_Data!$K:$K,E$3) | F6: =COUNTIFS(Clean_Data!$D:$D,$A6,Clean_Data!$K:$K,F$3) | G6: =SUM(B6:F6) | H6: =G6/G$13
A7: tanker | B7: =COUNTIFS(Clean_Data!$D:$D,$A7,Clean_Data!$K:$K,B$3) | C7: =COUNTIFS(Clean_Data!$D:$D,$A7,Clean_Data!$K:$K,C$3) | D7: =COUNTIFS(Clean_Data!$D:$D,$A7,Clean_Data!$K:$K,D$3) | E7: =COUNTIFS(Clean_Data!$D:$D,$A7,Clean_Data!$K:$K,E$3) | F7: =COUNTIFS(Clean_Data!$D:$D,$A7,Clean_Data!$K:$K,F$3) | G7: =SUM(B7:F7) | H7: =G7/G$13
A8: pleasure | B8: =COUNTIFS(Clean_Data!$D:$D,$A8,Clean_Data!$K:$K,B$3) | C8: =COUNTIFS(Clean_Data!$D:$D,$A8,Clean_Data!$K:$K,C$3) | D8: =COUNTIFS(Clean_Data!$D:$D,$A8,Clean_Data!$K:$K,D$3) | E8: =COUNTIFS(Clean_Data!$D:$D,$A8,Clean_Data!$K:$K,E$3) | F8: =COUNTIFS(Clean_Data!$D:$D,$A8,Clean_Data!$K:$K,F$3) | G8: =SUM(B8:F8) | H8: =G8/G$13
A9: tug | B9: =COUNTIFS(Clean_Data!$D:$D,$A9,Clean_Data!$K:$K,B$3) | C9: =COUNTIFS(Clean_Data!$D:$D,$A9,Clean_Data!$K:$K,C$3) | D9: =COUNTIFS(Clean_Data!$D:$D,$A9,Clean_Data!$K:$K,D$3) | E9: =COUNTIFS(Clean_Data!$D:$D,$A9,Clean_Data!$K:$K,E$3) | F9: =COUNTIFS(Clean_Data!$D:$D,$A9,Clean_Data!$K:$K,F$3) | G9: =SUM(B9:F9) | H9: =G9/G$13
A10: fishing | B10: =COUNTIFS(Clean_Data!$D:$D,$A10,Clean_Data!$K:$K,B$3) | C10: =COUNTIFS(Clean_Data!$D:$D,$A10,Clean_Data!$K:$K,C$3) | D10: =COUNTIFS(Clean_Data!$D:$D,$A10,Clean_Data!$K:$K,D$3) | E10: =COUNTIFS(Clean_Data!$D:$D,$A10,Clean_Data!$K:$K,E$3) | F10: =COUNTIFS(Clean_Data!$D:$D,$A10,Clean_Data!$K:$K,F$3) | G10: =SUM(B10:F10) | H10: =G10/G$13
A11: unknown | B11: =COUNTIFS(Clean_Data!$D:$D,$A11,Clean_Data!$K:$K,B$3) | C11: =COUNTIFS(Clean_Data!$D:$D,$A11,Clean_Data!$K:$K,C$3) | D11: =COUNTIFS(Clean_Data!$D:$D,$A11,Clean_Data!$K:$K,D$3) | E11: =COUNTIFS(Clean_Data!$D:$D,$A11,Clean_Data!$K:$K,E$3) | F11: =COUNTIFS(Clean_Data!$D:$D,$A11,Clean_Data!$K:$K,F$3) | G11: =SUM(B11:F11) | H11: =G11/G$13
A12: official | B12: =COUNTIFS(Clean_Data!$D:$D,$A12,Clean_Data!$K:$K,B$3) | C12: =COUNTIFS(Clean_Data!$D:$D,$A12,Clean_Data!$K:$K,C$3) | D12: =COUNTIFS(Clean_Data!$D:$D,$A12,Clean_Data!$K:$K,D$3) | E12: =COUNTIFS(Clean_Data!$D:$D,$A12,Clean_Data!$K:$K,E$3) | F12: =COUNTIFS(Clean_Data!$D:$D,$A12,Clean_Data!$K:$K,F$3) | G12: =SUM(B12:F12) | H12: =G12/G$13
A13: Total | B13: =SUM(B4:B12) | C13: =SUM(C4:C12) | D13: =SUM(D4:D12) | E13: =SUM(E4:E12) | F13: =SUM(F4:F12) | G13: =SUM(G4:G12)
A15: Type profile (computed in Python)
A16: vessel_type | B16: ships | C16: share_pct | D16: pct_moving | E16: avg_speed_moving_kn | F16: pct_dark
A17: other | B17: 1733 | C17: 25.2 | D17: 11.9 | E17: 7.7 | F17: 0
A18: cargo | B18: 1723 | C18: 25.1 | D18: 21.8 | E18: 8.3 | F18: 0
A19: passenger | B19: 964 | C19: 14 | D19: 14 | E19: 5.7 | F19: 0
A20: tanker | B20: 887 | C20: 12.9 | D20: 29.2 | E20: 7.9 | F20: 0
A21: pleasure | B21: 438 | C21: 6.4 | D21: 2.3 | E21: 5.2 | F21: 0
A22: tug | B22: 419 | C22: 6.1 | D22: 8.6 | E22: 5.9 | F22: 0
A23: fishing | B23: 312 | C23: 4.5 | D23: 8 | E23: 5.1 | F23: 0
A24: unknown | B24: 221 | C24: 3.2 | D24: 36.7 | E24: 7.3 | F24: 0
A25: official | B25: 180 | C25: 2.6 | D25: 13.3 | E25: 8 | F25: 0

Sheet Flags
A1: flag | B1: ships | C1: share_pct
A2: Netherlands | B2: 4235 | C2: 61.6
A3: Germany | B3: 648 | C3: 9.4
A4: Belgium | B4: 451 | C4: 6.6
A5: United Kingdom | B5: 317 | C5: 4.6
A6: France | B6: 182 | C6: 2.6
A7: Portugal | B7: 97 | C7: 1.4
A8: Switzerland | B8: 93 | C8: 1.4
A9: Malta | B9: 88 | C9: 1.3
A10: Liberia | B10: 77 | C10: 1.1
A11: Cyprus | B11: 76 | C11: 1.1
A12: Panama | B12: 70 | C12: 1
A13: Denmark | B13: 62 | C13: 0.9
... A16: Luxembourg | B16: 49 | C16: 0.7

Sheet Segments
A1: segment | B1: ships | C1: pct_under_way | D1: pct_idle | E1: pct_at_berth | F1: pct_at_anchor | G1: waiting_near_hubs | H1: avg_speed_under_way_kn | I1: share_pct
A2: Cargo & tanker | B2: 2610 | C2: 24.3 | D2: 17.4 | E2: 51.1 | F2: 7.3 | G2: 73 | H2: 8.1 | I2: 38
A3: Other & unknown | B3: 2134 | C3: 14.6 | D3: 28.4 | E3: 45.1 | F3: 11.9 | G3: 102 | H3: 7.6 | I3: 31
A4: Passenger | B4: 964 | C4: 14 | D4: 47.5 | E4: 26.9 | F4: 11.6 | G4: 51 | H4: 5.7 | I4: 14
A5: Pleasure & fishing | B5: 750 | C5: 4.7 | D5: 44.5 | E5: 39.3 | F5: 11.5 | G5: 27 | H5: 5.1 | I5: 10.9
A6: Tug | B6: 419 | C6: 8.6 | D6: 38.7 | E6: 40.8 | F6: 11.9 | G6: 22 | H6: 5.9 | I6: 6.1

Sheet Routes
A1: departure_port | B1: destination | C1: ships | D1: avg_speed_kn
A2: Antwerpen | B2: Antwerp | C2: 23 | D2: 2.2
A3: Europoort | B3: Rotterdam | C3: 20 | D3: 2.1
A4: Vlaardingen | B4: Rotterdam | C4: 18 | D4: 1.1
A5: Maassluis | B5: Rotterdam | C5: 17 | D5: 1.9
A6: Amsterdam | B6: Amsterdam | C6: 11 | D6: 2.1
A7: Hoek Van Holland | B7: Rotterdam | C7: 11 | D7: 3.4
A8: Schiedam | B8: Rotterdam | C8: 11 | D8: 3.5
A9: Zaandam | B9: Amsterdam | C9: 10 | D9: 1.2
A10: Rotterdam | B10: Rotterdam | C10: 9 | D10: 3.4
A11: Antwerpen | B11: Amsterdam | C11: 8 | D11: 6.4
A12: Zaandam | B12: Rotterdam | C12: 8 | D12: 5.9
A13: Bremerhaven | B13: Bremerhaven | C13: 6 | D13: 0
... A16: Antwerpen | B16: Rotterdam | C16: 4 | D16: 6.5
A18: Departure ports are detected live (ship leaves a known port while the backend is watching); destinations are typed by captains.

Sheet Data_Quality
A1: rule | B1: rows_affected | C1: action
A2: Raw rows received | B2: 8881 | C2: -
A3: Missing MMSI (cannot identify the ship) | B3: 0 | C3: dropped
A4: Duplicate MMSI (same ship twice) | B4: 0 | C4: dropped, kept the most recent report
A5: Missing or impossible position | B5: 0 | C5: dropped
A6: Position outside the tracked box | B6: 0 | C6: dropped
A7: Speed = 102.3 kn (AIS 'not available' code) | B7: 17 | C7: set to missing
A8: Negative speed | B8: 0 | C8: set to missing
A9: Implausible speed (> 40 kn) | B9: 14 | C9: set to missing
A10: Vessel type missing | B10: 1035 | C10: labelled 'unknown' (kept)
A11: Ship name missing or 'Unknown' | B11: 423 | C11: name set to missing (kept)
A12: Flag state missing (MMSI country code not recognised) | B12: 34 | C12: labelled 'Unknown' (kept)
A13: IMO = 0 (placeholder) | B13: 0 | C13: set to missing
... A23: Clean rows kept | B23: 8881 | C23: -
A26: field | B26: pct_complete | C26: ships
A27: Ship name | B27: 99.4 | C27: 6833
A28: Flag state | B28: 99.9 | C28: 6869
A29: Vessel type | B29: 96.8 | C29: 6656
A30: IMO number | B30: 26.5 | C30: 1823
A31: IMO passes checksum | B31: 25.5 | C31: 1757
A32: Call sign | B32: 96.1 | C32: 6611
A33: Length | B33: 95.2 | C33: 6546
A34: Speed | B34: 99.8 | C34: 6862
A35: Destination usable (not blank/placeholder) | B35: 79 | C35: 5434
A36: Destination resolved to a port | B36: 35.7 | C36: 2454

Sheet Assumptions
A1: Assumptions (blue = input you can change; yellow = key assumption)
A2: All values are published figures or clearly marked analyst assumptions. Nothing here is measured from AIS.
A4: parameter | B4: size_class | C4: low | D4: central | E4: high | F4: unit | G4: source | H4: note
A5: fuel_at_anchor_t_per_day | B5: small (<100 m) | C5: 0.3 | D5: 0.8 | E5: 2 | F5: tonnes/day/ship | G5: Analyst assumption: no published at-anchor figure by ship size exists. Bracketed by: auxiliary-engine use of 0.5-1 t/day for 40-70k DWT tramp ships (Journal of Shipping and Trade, doi 10.1186/s41072-021-00097-z and 10.1186/s41072-017-0021-y); about 4 t/day auxiliary for a large container ship at sea (maritimepage.com/fuel-consumption-how-much-fuel-cargo-ship-use); 9.4 t/day in port including cargo operations for a 19k DWT tanker (doi 10.1186/s41072-018-0031-4). | H5: Ships at anchor run auxiliary engines and boilers only; replace with company data if available. Unknown size uses the medium-class values.
A6: fuel_at_anchor_t_per_day | B6: medium (100-200 m) | C6: 1 | D6: 2.5 | E6: 5 | F6: tonnes/day/ship | G6: Analyst assumption: no published at-anchor figure by ship size exists. Bracketed by: auxiliary-engine use of 0.5-1 t/day for 40-70k DWT tramp ships (Journal of Shipping and Trade, doi 10.1186/s41072-021-00097-z and 10.1186/s41072-017-0021-y); about 4 t/day auxiliary for a large container ship at sea (maritimepage.com/fuel-consumption-how-much-fuel-cargo-ship-use); 9.4 t/day in port including cargo operations for a 19k DWT tanker (doi 10.1186/s41072-018-0031-4). | H6: Ships at anchor run auxiliary engines and boilers only; replace with company data if available. Unknown size uses the medium-class values.
A7: fuel_at_anchor_t_per_day | B7: large (200-300 m) | C7: 2 | D7: 4 | E7: 9 | F7: tonnes/day/ship | G7: Analyst assumption: no published at-anchor figure by ship size exists. Bracketed by: auxiliary-engine use of 0.5-1 t/day for 40-70k DWT tramp ships (Journal of Shipping and Trade, doi 10.1186/s41072-021-00097-z and 10.1186/s41072-017-0021-y); about 4 t/day auxiliary for a large container ship at sea (maritimepage.com/fuel-consumption-how-much-fuel-cargo-ship-use); 9.4 t/day in port including cargo operations for a 19k DWT tanker (doi 10.1186/s41072-018-0031-4). | H7: Ships at anchor run auxiliary engines and boilers only; replace with company data if available. Unknown size uses the medium-class values.
A8: fuel_at_anchor_t_per_day | B8: very large (>300 m) | C8: 3 | D8: 6 | E8: 12 | F8: tonnes/day/ship | G8: Analyst assumption: no published at-anchor figure by ship size exists. Bracketed by: auxiliary-engine use of 0.5-1 t/day for 40-70k DWT tramp ships (Journal of Shipping and Trade, doi 10.1186/s41072-021-00097-z and 10.1186/s41072-017-0021-y); about 4 t/day auxiliary for a large container ship at sea (maritimepage.com/fuel-consumption-how-much-fuel-cargo-ship-use); 9.4 t/day in port including cargo operations for a 19k DWT tanker (doi 10.1186/s41072-018-0031-4). | H8: Ships at anchor run auxiliary engines and boilers only; replace with company data if available. Unknown size uses the medium-class values.
A9: fuel_at_anchor_t_per_day | B9: unknown size | C9: 1 | D9: 2.5 | E9: 5 | F9: tonnes/day/ship | G9: Analyst assumption: no published at-anchor figure by ship size exists. Bracketed by: auxiliary-engine use of 0.5-1 t/day for 40-70k DWT tramp ships (Journal of Shipping and Trade, doi 10.1186/s41072-021-00097-z and 10.1186/s41072-017-0021-y); about 4 t/day auxiliary for a large container ship at sea (maritimepage.com/fuel-consumption-how-much-fuel-cargo-ship-use); 9.4 t/day in port including cargo operations for a 19k DWT tanker (doi 10.1186/s41072-018-0031-4). | H9: Ships at anchor run auxiliary engines and boilers only; replace with company data if available. Unknown size uses the medium-class values.
A10: fuel_price_usd_per_t | B10: all | C10: 880 | D10: 1328 | E10: 1500 | F10: USD/tonne | G10: Ship & Bunker 6 Oct 2026: 20-port average VLSFO $876.50/mt and MGO $1,500/mt (via shipuniverse.com/?p=22139); Rotterdam conventional LSMGO about $1,328/mt, derived from ENGINE 2 Oct 2026 (B30-LSMGO $1,398 less a $70 premium). | H10: The North Sea and English Channel are a 0.10% sulphur Emission Control Area, so MGO-type fuel is the central case; low is the VLSFO benchmark.
A11: co2_t_per_t_fuel | B11: all | C11: 3.114 | D11: 3.206 | E11: 3.206 | F11: t CO2 per t fuel | G11: EU Regulation 2015/757 as amended by Delegated Regulation 2016/2071: HFO 3.114, LFO 3.151, MGO 3.206 t CO2 per t fuel (legislation.gov.uk/eur/2016/2071). | H11: Tank-to-wake CO2 only; methane and N2O not included.
A12: vessel_opex_usd_per_day | B12: all | C12: 5000 | D12: 7474 | E12: 10000 | F12: USD/day/ship | G12: Low: running cost of $5,000/day in the tramp-ship tables (doi 10.1186/s41072-017-0021-y). Central: Drewry average daily operating cost across 47 ship types and sizes, $7,474 in 2022 (marinelog.com). High: analyst assumption for larger or more complex ships. | H12: Owner running cost (crew, insurance, maintenance). Excludes fuel and charter hire, so cost of delay is conservative.

Sheet Estimates
A1: ESTIMATE: daily fuel, CO2 and cost of ships waiting at anchor near a hub
A2: These are estimates built from the Assumptions sheet, not measurements. Low uses every low assumption together, high every high one, so the range is wide on purpose.
A4: Size class | B4: Ships waiting | C4: Fuel t/day low | D4: Fuel t/day central | E4: Fuel t/day high | F4: CO2 t/day low | G4: CO2 t/day central | H4: CO2 t/day high | I4: Cost USD/day low | J4: Cost USD/day central | K4: Cost USD/day high
A5: small (<100 m) | B5: =COUNTIFS(Clean_Data!$K:$K,"at_anchor",Clean_Data!$AC:$AC,"<>",Clean_Data!$AB:$AB,$A5) | C5: =$B5*Assumptions!$C$5 | D5: =$B5*Assumptions!$D$5 | E5: =$B5*Assumptions!$E$5 | F5: =C5*Assumptions!$C$11 | G5: =D5*Assumptions!$D$11 | H5: =E5*Assumptions!$E$11 | I5: =$B5*(Assumptions!$C$12+Assumptions!$C$5*Assumptions!$C$10) | J5: =$B5*(Assumptions!$D$12+Assumptions!$D$5*Assumptions!$D$10) | K5: =$B5*(Assumptions!$E$12+Assumptions!$E$5*Assumptions!$E$10)
A6: medium (100-200 m) | B6: =COUNTIFS(Clean_Data!$K:$K,"at_anchor",Clean_Data!$AC:$AC,"<>",Clean_Data!$AB:$AB,$A6) | C6: =$B6*Assumptions!$C$6 | D6: =$B6*Assumptions!$D$6 | E6: =$B6*Assumptions!$E$6 | F6: =C6*Assumptions!$C$11 | G6: =D6*Assumptions!$D$11 | H6: =E6*Assumptions!$E$11 | I6: =$B6*(Assumptions!$C$12+Assumptions!$C$6*Assumptions!$C$10) | J6: =$B6*(Assumptions!$D$12+Assumptions!$D$6*Assumptions!$D$10) | K6: =$B6*(Assumptions!$E$12+Assumptions!$E$6*Assumptions!$E$10)
A7: large (200-300 m) | B7: =COUNTIFS(Clean_Data!$K:$K,"at_anchor",Clean_Data!$AC:$AC,"<>",Clean_Data!$AB:$AB,$A7) | C7: =$B7*Assumptions!$C$7 | D7: =$B7*Assumptions!$D$7 | E7: =$B7*Assumptions!$E$7 | F7: =C7*Assumptions!$C$11 | G7: =D7*Assumptions!$D$11 | H7: =E7*Assumptions!$E$11 | I7: =$B7*(Assumptions!$C$12+Assumptions!$C$7*Assumptions!$C$10) | J7: =$B7*(Assumptions!$D$12+Assumptions!$D$7*Assumptions!$D$10) | K7: =$B7*(Assumptions!$E$12+Assumptions!$E$7*Assumptions!$E$10)
A8: very large (>300 m) | B8: =COUNTIFS(Clean_Data!$K:$K,"at_anchor",Clean_Data!$AC:$AC,"<>",Clean_Data!$AB:$AB,$A8) | C8: =$B8*Assumptions!$C$8 | D8: =$B8*Assumptions!$D$8 | E8: =$B8*Assumptions!$E$8 | F8: =C8*Assumptions!$C$11 | G8: =D8*Assumptions!$D$11 | H8: =E8*Assumptions!$E$11 | I8: =$B8*(Assumptions!$C$12+Assumptions!$C$8*Assumptions!$C$10) | J8: =$B8*(Assumptions!$D$12+Assumptions!$D$8*Assumptions!$D$10) | K8: =$B8*(Assumptions!$E$12+Assumptions!$E$8*Assumptions!$E$10)
A9: unknown size | B9: =COUNTIFS(Clean_Data!$K:$K,"at_anchor",Clean_Data!$AC:$AC,"<>",Clean_Data!$AB:$AB,$A9) | C9: =$B9*Assumptions!$C$9 | D9: =$B9*Assumptions!$D$9 | E9: =$B9*Assumptions!$E$9 | F9: =C9*Assumptions!$C$11 | G9: =D9*Assumptions!$D$11 | H9: =E9*Assumptions!$E$11 | I9: =$B9*(Assumptions!$C$12+Assumptions!$C$9*Assumptions!$C$10) | J9: =$B9*(Assumptions!$D$12+Assumptions!$D$9*Assumptions!$D$10) | K9: =$B9*(Assumptions!$E$12+Assumptions!$E$9*Assumptions!$E$10)
A10: Total | B10: =SUM(B5:B9) | C10: =SUM(C5:C9) | D10: =SUM(D5:D9) | E10: =SUM(E5:E9) | F10: =SUM(F5:F9) | G10: =SUM(G5:G9) | H10: =SUM(H5:H9) | I10: =SUM(I5:I9) | ... K10: =SUM(K5:K9)
A12: How to read: cost = ships x (vessel running cost per day + fuel per day x fuel price). Fuel = ships x fuel at anchor per day. CO2 = fuel x emission factor.
A13: This is the cost of ships sitting at anchor near a hub on a typical day. It is an upper bound for congestion-attributable cost, because some waiting is normal.
A14: A real congestion cost needs a baseline of normal waiting (see the time analysis once the history collector has run for several weeks).
A15: AIS contains no operator, cargo or schedule data, so no company-level loss can be computed.

Sheet Clean_Data
A1: mmsi | B1: name | C1: flag | D1: vessel_type | E1: imo | F1: imo_valid | G1: call_sign | H1: lat | I1: lng | J1: status | K1: status_group | L1: speed | M1: heading | N1: minutes_since_update | O1: is_stale | P1: is_dark_flagged | Q1: destination | R1: dest_clean | S1: dest_quality | T1: dest_hub | U1: dest_resolved | V1: destination_port | W1: eta | X1: departure_port | Y1: departure_time | Z1: length_m | AA1: beam_m | AB1: size_class | AC1: hub | AD1: zone | AE1: region | AF1: dist_to_hub_km | AG1: is_edge | AH1: stationary_but_moving | AI1: moving_but_anchored
A2: 246344000 | B2: VB COURAGE | C2: Netherlands | D2: tug | E2: 9963891 | F2: 1 | G2: PHZY | H2: 51.91664 | I2: 4.21994 | J2: moving | K2: moving | L2: 6.1 | M2: 146.7 | N2: 0 | O2: 0 | P2: 0 | Q2: HARBOR TOWAGE | R2: HARBOR TOWAGE | S2: other_text | Z2: 28 | AA2: 13 | AB2: small (<100 m) | AC2: Rotterdam | AD2: Benelux coast | AE2: North Sea & English Channel | AF2: 9.021096 | AG2: 0 | AH2: 0 | AI2: 0
A3: 244060223 | B3: THREE POINT 4 | C3: Netherlands | D3: pleasure | F3: 0 | G3: PC6003 | H3: 51.82074 | I3: 4.04951 | J3: anchored-sea | K3: at_anchor | L3: 0 | N3: 0 | O3: 0 | P3: 0 | S3: missing | Z3: 26 | AA3: 7 | AB3: small (<100 m) | AC3: Rotterdam | AD3: Benelux coast | AE3: North Sea & English Channel | AF3: 14.784914 | AG3: 0 | AH3: 0 | AI3: 0
A4: 244770296 | B4: FOSTA | C4: Netherlands | D4: pleasure | F4: 0 | G4: PH7186 | H4: 53.18726 | I4: 7.20234 | J4: anchored-sea | K4: at_anchor | L4: 0 | M4: 0 | N4: 0 | O4: 0 | P4: 0 | S4: missing | W4: 01-01 00:00 UTC | Z4: 23 | AA4: 5 | AB4: small (<100 m) | AE4: North Sea & English Channel | AG4: 0 | AH4: 0 | AI4: 0
A5: 244740200 | B5: MAAIKE | C5: Netherlands | D5: tanker | F5: 0 | G5: PC2246 | H5: 51.91265 | I5: 4.41838 | J5: moving | K5: idle | L5: 0 | M5: 0 | N5: 0 | O5: 0 | P5: 0 | S5: missing | W5: 05-05 16:28 UTC | Z5: 57 | AA5: 12 | AB5: small (<100 m) | AC5: Rotterdam | AD5: Benelux coast | AE5: North Sea & English Channel | AF5: 22.220796 | AG5: 0 | AH5: 1 | AI5: 0
A6: 230196150 | B6: TARMO | C6: Finland | D6: pleasure | F6: 0 | G6: OHA7234 | H6: 51.55138 | I6: 3.81298 | J6: moving | K6: idle | L6: 0 | N6: 0 | O6: 0 | P6: 0 | Q6: DORDRECHT | R6: DORDRECHT | S6: other_text | U6: DORDRECHT | V6: DORDRECHT | W6: 04-03 12:30 UTC | Z6: 20 | AA6: 5 | AB6: small (<100 m) | AE6: North Sea & English Channel | AG6: 0 | AH6: 1 | AI6: 0
A7: 246327000 | B7: HD35 NOORDERLICHT | C7: Netherlands | D7: fishing | E7: 9115963 | F7: 1 | G7: PDPH | H7: 52.95074 | I7: 4.78561 | J7: moving | K7: idle | L7: 0 | N7: 0 | O7: 0 | P7: 0 | Q7: SEA | R7: SEA | S7: other_text | U7: EDINBURGH OF THE SEVEN SEAS | V7: EDINBURGH OF THE SEVEN SEAS | W7: 01-19 00:00 UTC | Z7: 24 | AA7: 6 | AB7: small (<100 m) | AE7: North Sea & English Channel | AG7: 0 | AH7: 1 | AI7: 0
A8: 244700469 | B8: CARLIJN | C8: Netherlands | D8: cargo | F8: 0 | G8: PE8492 | H8: 52.48828 | I8: 5.33218 | J8: moving | K8: moving | L8: 6.1 | M8: 57 | N8: 0 | O8: 0 | P8: 0 | Q8: ZWARTE WATER | R8: ZWARTE WATER | S8: other_text | W8: 10-11 19:29 UTC | X8: ZAANDAM | Y8: 2026-10-11T05:55:25.285242+00:00 | Z8: 86 | AA8: 11 | AB8: small (<100 m) | AE8: North Sea & English Channel | AG8: 0 | AH8: 0 | AI8: 0
A9: 244084000 | B9: TENDER I | C9: Netherlands | D9: other | E9: 8134039 | F9: 1 | G9: PHXT | H9: 52.46451 | I9: 4.59495 | J9: anchored-sea | K9: at_anchor | L9: 0.1 | M9: 192.1 | N9: 0 | O9: 0 | P9: 0 | S9: missing | Z9: 41 | AA9: 7 | AB9: small (<100 m) | AC9: IJmuiden | AD9: Benelux coast | AE9: North Sea & English Channel | AF9: 1.1302051 | AG9: 0 | AH9: 0 | AI9: 0
A10: 244660833 | B10: VRIENDSCHAP | C10: Netherlands | D10: pleasure | F10: 0 | G10: PH3173 | H10: 52.45979 | I10: 5.03875 | J10: anchored-sea | K10: at_anchor | L10: 0 | M10: 302.2 | N10: 0 | O10: 0 | P10: 0 | Q10: MONNICKENDAM | R10: MONNICKENDAM | S10: other_text | Z10: 32 | AA10: 6 | AB10: small (<100 m) | AE10: North Sea & English Channel | AG10: 0 | AH10: 0 | AI10: 0
A11: 244078768 | B11: HILDA S | C11: Netherlands | D11: tanker | F11: 0 | G11: PF6761 | H11: 51.8207 | I11: 4.69163 | J11: moving | K11: idle | L11: 0.1 | M11: 113.4 | N11: 0 | O11: 0 | P11: 0 | S11: missing | Z11: 35 | AA11: 7 | AB11: small (<100 m) | AE11: North Sea & English Channel | AG11: 0 | AH11: 1 | AI11: 0
A12: 235005350 | B12: QUO VADIS | C12: United Kingdom | D12: fishing | E12: 9101223 | F12: 1 | G12: VQHP9 | H12: 53.17938 | I12: 5.41462 | J12: moving | K12: idle | L12: 0 | M12: 251.8 | N12: 0 | O12: 0 | P12: 0 | Q12: FISHGROUNDS | R12: FISHGROUNDS | S12: other_text | Z12: 43 | AA12: 8 | AB12: small (<100 m) | AE12: North Sea & English Channel | AG12: 0 | AH12: 1 | AI12: 0
A13: 244660659 | B13: AEGIR | C13: Netherlands | D13: other | F13: 0 | G13: PD2303 | H13: 53.0505 | I13: 5.39918 | J13: moving | K13: idle | L13: 0 | N13: 0 | O13: 0 | P13: 0 | Q13: MAKKUM | R13: MAKKUM | S13: other_text | W13: 04-16 14:00 UTC | Z13: 20 | AA13: 6 | AB13: small (<100 m) | AE13: North Sea & English Channel | AG13: 0 | AH13: 1 | AI13: 0
A14: 269057062 | B14: KINGSTON | C14: Switzerland | D14: tanker | F14: 0 | G14: HE7062 | H14: 52.02164 | I14: 5.11416 | J14: moving | K14: moving | L14: 0.9 | M14: 195.8 | N14: 0 | O14: 0 | P14: 0 | Q14: ATM MOERDIJK | R14: ATM MOERDIJK | S14: other_text | W14: 10-11 12:23 UTC | X14: ZAANDAM | Y14: 2026-10-11T05:54:17.441638+00:00 | Z14: 86 | AA14: 10 | AB14: small (<100 m) | AE14: North Sea & English Channel | AG14: 0 | AH14: 0 | AI14: 0
A15: 244770588 | B15: PIETERNELLA | C15: Netherlands | D15: cargo | F15: 0 | G15: PE6551 | H15: 51.97223 | I15: 5.30563 | J15: moving | K15: idle | L15: 0 | M15: 230.7 | N15: 0 | O15: 0 | P15: 0 | Q15: URK | R15: URK | S15: other_text | U15: GRAND TURK | V15: GRAND TURK | W15: 07-23 00:00 UTC | Z15: 75 | AA15: 8 | AB15: small (<100 m) | AE15: North Sea & English Channel | AG15: 0 | AH15: 1 | AI15: 0
A16: 244870902 | B16: EQUILIBRE | C16: Netherlands | D16: pleasure | F16: 0 | G16: PB3774 | H16: 51.22882 | I16: 4.40612 | J16: moving | K16: idle | L16: 0 | N16: 0 | O16: 0 | P16: 0 | Q16: ANTWERPEN | R16: ANTWERPEN | S16: hub_name | T16: Antwerp | U16: Antwerp | V16: ANTWERPEN | Z16: 21 | AA16: 6 | AB16: small (<100 m) | AC16: Antwerp | AD16: Benelux coast | AE16: North Sea & English Channel | AF16: 7.002575 | AG16: 0 | AH16: 1 | AI16: 0
A17: 205375690 | B17: ACALI | C17: Belgium | D17: cargo | F17: 0 | G17: OT3756 | H17: 51.23907 | I17: 4.46932 | J17: anchored-sea | K17: at_anchor | L17: 0 | N17: 0 | O17: 0 | P17: 0 | Q17: ANTWERPEN PSA ANTWE | R17: ANTWERPEN PSA ANTWE | S17: hub_name | T17: Antwerp | U17: Antwerp | V17: ANTWERPEN | W17: 10-02 04:06 UTC | Z17: 196 | AA17: 12 | AB17: medium (100-200 m) | AC17: Antwerp | AD17: Benelux coast | AE17: North Sea & English Channel | AF17: 10.287582 | AG17: 0 | AH17: 0 | AI17: 0
A18: 244010025 | B18: PIET HEIN | C18: Netherlands | D18: passenger | F18: 0 | G18: PD2717 | H18: 51.90869 | I18: 4.48231 | J18: moving | K18: idle | L18: 0.1 | M18: 357.4 | N18: 0 | O18: 0 | P18: 0 | Q18: ROTTERDAM | R18: ROTTERDAM | S18: hub_name | T18: Rotterdam | U18: Rotterdam | V18: ROTTERDAM | W18: 01-31 21:00 UTC | Z18: 38 | AA18: 10 | AB18: small (<100 m) | AC18: Rotterdam | AD18: Benelux coast | AE18: North Sea & English Channel | AF18: 26.613054 | AG18: 0 | AH18: 1 | AI18: 0
A19: 244670420 | B19: HOOP DOET LEVEN | C19: Netherlands | D19: passenger | F19: 0 | G19: PC2473 | H19: 52.87989 | I19: 5.36687 | J19: anchored-sea | K19: at_anchor | L19: 0 | M19: 249.2 | N19: 0 | O19: 0 | P19: 0 | Q19: LEEUWARDEN | R19: LEEUWARDEN | S19: other_text | W19: 04-16 15:10 UTC | Z19: 28 | AA19: 5 | AB19: small (<100 m) | AE19: North Sea & English Channel | AG19: 0 | AH19: 0 | AI19: 0
A20: 244830939 | B20: ZK9 ANTONIA | C20: Netherlands | D20: fishing | F20: 0 | G20: PA6790 | H20: 53.40793 | I20: 6.20022 | J20: moving | K20: idle | L20: 0 | N20: 0 | O20: 0 | P20: 0 | Q20: LAUWERSOOG | R20: LAUWERSOOG | S20: other_text | W20: 08-09 12:45 UTC | Z20: 19 | AA20: 5 | AB20: small (<100 m) | AE20: North Sea & English Channel | AG20: 0 | AH20: 1 | AI20: 0
A21: 245617000 | B21: OD3 ADRIANNE | C21: Netherlands | D21: fishing | E21: 8008371 | F21: 1 | G21: PFWH | H21: 51.82532 | I21: 4.03332 | J21: moving | K21: idle | L21: 0.1 | M21: 307.8 | N21: 0 | O21: 0 | P21: 0 | Q21: STELLENDAM | R21: STELLENDAM | S21: other_text | Z21: 24 | AA21: 6 | AB21: small (<100 m) | AC21: Rotterdam | AD21: Benelux coast | AE21: North Sea & English Channel | AF21: 14.59956 | AG21: 0 | AH21: 1 | AI21: 0
A22: 244376506 | B22: NZK PONT 103 | C22: Netherlands | D22: passenger | F22: 0 | G22: PE5688 | H22: 52.46292 | I22: 4.63222 | J22: anchored-port | K22: at_berth | L22: 0 | N22: 0 | O22: 0 | P22: 0 | Q22: VELSEN8NZ | R22: VELSEN8NZ | S22: other_text | W22: 06-02 00:51 UTC | X22: IJMUIDEN | Y22: 2026-10-11T08:14:09.343383+00:00 | Z22: 42 | AA22: 15 | AB22: small (<100 m) | AC22: IJmuiden | AD22: Benelux coast | AE22: North Sea & English Channel | AF22: 3.552804 | AG22: 0 | AH22: 0 | AI22: 0
A23: 244730446 | B23: LEANDER | C23: Netherlands | D23: other | F23: 0 | G23: PB9533 | H23: 51.23943 | I23: 4.41852 | J23: anchored-sea | K23: at_anchor | L23: 0 | N23: 0 | O23: 0 | P23: 0 | S23: missing | Z23: 13 | AA23: 5 | AB23: small (<100 m) | AC23: Antwerp | AD23: Benelux coast | AE23: North Sea & English Channel | AF23: 7.0359359 | AG23: 0 | AH23: 0 | AI23: 0
A24: 256002474 | B24: BARBAROSSA I | C24: Malta | D24: other | F24: 0 | G24: 9HA5570 | H24: 53.33266 | I24: 6.93458 | J24: anchored-sea | K24: at_anchor | L24: 0 | N24: 0 | O24: 0 | P24: 0 | Q24: NORDERNEY | R24: NORDERNEY | S24: other_text | W24: 08-13 08:30 UTC | Z24: 68 | AA24: 30 | AB24: small (<100 m) | AC24: Eemshaven | AD24: German Bight & Ems | AE24: North Sea & English Channel | AF24: 14.476687 | AG24: 0 | AH24: 0 | AI24: 0
A25: 244704000 | B25: UK225 AUKE SENIOR | C25: Netherlands | D25: fishing | E25: 9856517 | F25: 1 | G25: PCWI | H25: 53.4562 | I25: 6.82485 | J25: moving | K25: idle | L25: 0 | M25: 276 | N25: 0 | O25: 0 | P25: 0 | Q25: EEMSHAVEN | R25: EEMSHAVEN | S25: hub_name | T25: Eemshaven | U25: Eemshaven | V25: EEMSHAVEN | Z25: 30 | AA25: 9 | AB25: small (<100 m) | AC25: Eemshaven | AD25: German Bight & Ems | AE25: North Sea & English Channel | AF25: 1.2172079 | AG25: 0 | AH25: 1 | AI25: 0
A26: 244740568 | B26: LINQUENDA-II | C26: Netherlands | D26: passenger | F26: 0 | G26: @WV304 | H26: 51.82103 | I26: 4.12859 | J26: anchored-sea | K26: at_anchor | L26: 0 | N26: 0 | O26: 0 | P26: 0 | Q26: HELLEVOETSLUIS | R26: HELLEVOETSLUIS | S26: other_text | W26: 10-15 16:00 UTC | Z26: 25 | AA26: 6 | AB26: small (<100 m) | AC26: Rotterdam | AD26: Benelux coast | AE26: North Sea & English Channel | AF26: 14.474451 | AG26: 0 | AH26: 0 | AI26: 0
A27: 244210287 | B27: JACKSON 2 | C27: Netherlands | D27: passenger | F27: 0 | G27: PF4419 | H27: 52.38563 | I27: 4.89051 | J27: anchored-sea | K27: at_anchor | L27: 0 | N27: 0 | O27: 0 | P27: 0 | S27: missing | Z27: 7 | AA27: 4 | AB27: small (<100 m) | AC27: Amsterdam | AD27: Benelux coast | AE27: North Sea & English Channel | AF27: 5.0443055 | AG27: 0 | AH27: 0 | AI27: 0
A28: 244660628 | B28: MI-ARENA | C28: Netherlands | D28: other | F28: 0 | G28: PE6969 | H28: 51.3217 | I28: 3.82053 | J28: moving | K28: idle | L28: 0 | N28: 0 | O28: 0 | P28: 0 | S28: missing | Z28: 80 | AA28: 9 | AB28: small (<100 m) | AC28: Terneuzen | AD28: Benelux coast | AE28: North Sea & English Channel | AF28: 1.1334773 | AG28: 0 | AH28: 1 | AI28: 0
A29: 244020020 | B29: BLACK BETTY | C29: Netherlands | D29: passenger | F29: 0 | G29: PA3107 | H29: 53.17576 | I29: 5.41295 | J29: anchored-sea | K29: at_anchor | L29: 0 | N29: 0 | O29: 0 | P29: 0 | S29: missing | Z29: 25 | AA29: 6 | AB29: small (<100 m) | AE29: North Sea & English Channel | AG29: 0 | AH29: 0 | AI29: 0
A30: 244710927 | B30: JEANNET | C30: Netherlands | D30: cargo | F30: 0 | G30: PH3275 | H30: 51.69748 | I30: 4.41974 | J30: anchored-sea | K30: at_anchor | L30: 0 | N30: 0 | O30: 0 | P30: 0 | Q30: GAVERE BOVENSCHELDE | R30: GAVERE BOVENSCHELDE | S30: other_text | W30: 10-10 06:17 UTC | Z30: 85 | AA30: 9 | AB30: small (<100 m) | AE30: North Sea & English Channel | AG30: 0 | AH30: 0 | AI30: 0
A31: 246840000 | B31: KG-8 ENSIS | C31: Netherlands | D31: fishing | E31: 9958248 | F31: 1 | G31: PFTF | H31: 51.61672 | I31: 3.68968 | J31: moving | K31: idle | L31: 0 | M31: 116.4 | N31: 0 | O31: 0 | P31: 0 | Q31: FISHING GROUNDS | R31: FISHING GROUNDS | S31: other_text | Z31: 25 | AA31: 8 | AB31: small (<100 m) | AE31: North Sea & English Channel | AG31: 0 | AH31: 1 | AI31: 0
A32: 244710579 | B32: BRAM | C32: Netherlands | D32: tug | F32: 0 | G32: PI9166 | H32: 52.42033 | I32: 4.84602 | J32: moving | K32: idle | L32: 0 | M32: 278.8 | N32: 0 | O32: 0 | P32: 0 | Q32: THUISHAVEN | R32: THUISHAVEN | S32: other_text | Z32: 23 | AA32: 6 | AB32: small (<100 m) | AC32: Amsterdam | AD32: Benelux coast | AE32: North Sea & English Channel | AF32: 2.8679697 | AG32: 0 | AH32: 1 | AI32: 0
A33: 244110350 | B33: LA REINE | C33: Netherlands | D33: passenger | F33: 0 | G33: PE9619 | H33: 52.36003 | I33: 4.90478 | J33: moving | K33: idle | L33: 0.1 | N33: 0 | O33: 0 | P33: 0 | Q33: AMSTERDAM | R33: AMSTERDAM | S33: hub_name | T33: Amsterdam | U33: Amsterdam | V33: AMSTERDAM | Z33: 12 | AA33: 3 | AB33: small (<100 m) | AC33: Amsterdam | AD33: Benelux coast | AE33: North Sea & English Channel | AF33: 7.27102 | AG33: 0 | AH33: 1 | AI33: 0
A34: 244660069 | B34: LEGACY | C34: Netherlands | D34: cargo | F34: 0 | G34: PE9657 | H34: 51.90285 | I34: 5.54278 | J34: anchored-sea | K34: at_anchor | L34: 1.2 | M34: 78.5 | N34: 0 | O34: 0 | P34: 0 | Q34: HAFEN SCHWELGERN | R34: HAFEN SCHWELGERN | S34: other_text | W34: 10-11 08:18 UTC | Z34: 135 | AA34: 12 | AB34: medium (100-200 m) | AE34: North Sea & English Channel | AG34: 0 | AH34: 0 | AI34: 0
A35: 245217000 | B35: SVITZER JUPITER | C35: Netherlands | D35: tug | E35: 9878254 | F35: 1 | G35: PDSK | H35: 52.46144 | I35: 4.58792 | J35: moving | K35: idle | L35: 0.1 | M35: 59.4 | N35: 0 | O35: 0 | P35: 0 | Q35: IJMUIDEN/AMSTERDAM | R35: IJMUIDEN/AMSTERDAM | S35: hub_name | T35: Amsterdam | U35: Amsterdam | V35: AMSTERDAM | W35: 09-18 12:00 UTC | Z35: 23 | AA35: 12 | AB35: small (<100 m) | AC35: IJmuiden | AD35: Benelux coast | AE35: North Sea & English Channel | AF35: 0.55997462 | AG35: 0 | AH35: 1 | AI35: 0
A36: 244780112 | B36: BOTA FOGO | C36: Netherlands | D36: passenger | F36: 0 | G36: PF7734 | H36: 52.36977 | I36: 4.93734 | J36: moving | K36: idle | L36: 0 | N36: 0 | O36: 0 | P36: 0 | Q36: AMSTERDAM | R36: AMSTERDAM | S36: hub_name | T36: Amsterdam | U36: Amsterdam | V36: AMSTERDAM | Z36: 20 | AA36: 4 | AB36: small (<100 m) | AC36: Amsterdam | AD36: Benelux coast | AE36: North Sea & English Channel | AF36: 8.6440326 | AG36: 0 | AH36: 1 | AI36: 0
A37: 244013532 | B37: BRUUZER | C37: Netherlands | D37: passenger | F37: 0 | G37: PF6647 | H37: 53.04009 | I37: 4.84975 | J37: moving | K37: idle | L37: 0 | N37: 0 | O37: 0 | P37: 0 | Q37: OUDESCHILD | R37: OUDESCHILD | S37: other_text | W37: 04-15 04:30 UTC | Z37: 13 | AA37: 5 | AB37: small (<100 m) | AE37: North Sea & English Channel | AG37: 0 | AH37: 1 | AI37: 0
A38: 235053185 | B38: STAR CLIPPER | C38: United Kingdom | D38: other | F38: 0 | G38: MCJP5 | H38: 51.50744 | I38: 0.00684 | J38: moving | K38: idle | L38: 0 | M38: 46 | N38: 0 | O38: 0 | P38: 0 | Q38: DT#U@A49AFP@6/ E@P | R38: DT#U@A49AFP@6/ E@P | S38: other_text | AB38: unknown size | AE38: North Sea & English Channel | AG38: 0 | AH38: 1 | AI38: 0
A39: 244020365 | B39: NICKELINE | C39: Netherlands | D39: pleasure | F39: 0 | G39: PH2640 | H39: 51.92145 | I39: 4.49956 | J39: moving | K39: idle | L39: 0 | N39: 0 | O39: 0 | P39: 0 | Q39: ? | R39: ? | S39: junk | Z39: 26 | AA39: 6 | AB39: small (<100 m) | AC39: Rotterdam | AD39: Benelux coast | AE39: North Sea & English Channel | AF39: 27.575857 | AG39: 0 | AH39: 1 | AI39: 0
A40: 244750085 | B40: POOLSTER | C40: Netherlands | D40: passenger | F40: 0 | G40: PF7996 | H40: 53.17494 | I40: 5.41095 | J40: anchored-sea | K40: at_anchor | L40: 0 | M40: 219 | N40: 0 | O40: 0 | P40: 0 | S40: missing | Z40: 36 | AA40: 6 | AB40: small (<100 m) | AE40: North Sea & English Channel | AG40: 0 | AH40: 0 | AI40: 0
A41: 244170522 | B41: PETER | C41: Netherlands | D41: other | E41: 9842762 | F41: 1 | G41: PDKU | H41: 53.46775 | I41: 6.20198 | J41: moving | K41: moving | L41: 6.5 | M41: 63 | N41: 0 | O41: 0 | P41: 0 | Q41: LAUWERSOOG | R41: LAUWERSOOG | S41: other_text | W41: 10-03 11:30 UTC | Z41: 22 | AA41: 7 | AB41: small (<100 m) | AE41: North Sea & English Channel | AG41: 0 | AH41: 0 | AI41: 0
A42: 244730326 | B42: GREVELINGEN | C42: Netherlands | D42: passenger | F42: 0 | G42: PE8168 | H42: 51.743 | I42: 3.89038 | J42: moving | K42: idle | L42: 0 | M42: 339.2 | N42: 0 | O42: 0 | P42: 0 | Q42: GREVELINGEN | R42: GREVELINGEN | S42: other_text | W42: 07-09 15:00 UTC | Z42: 30 | AA42: 8 | AB42: small (<100 m) | AC42: Rotterdam | AD42: Benelux coast | AE42: North Sea & English Channel | AF42: 27.15036 | AG42: 0 | AH42: 1 | AI42: 0
A43: 212368000 | B43: FREEWAY | C43: Cyprus | D43: other | E43: 9691682 | F43: 1 | G43: 5BCX4 | H43: 51.57247 | I43: 3.96053 | J43: anchored-sea | K43: at_anchor | L43: 0.4 | M43: 207.1 | N43: 0 | O43: 0 | P43: 0 | Q43: HANSWEERT | R43: HANSWEERT | S43: other_text | U43: HANSWEERT | V43: HANSWEERT | W43: 09-28 15:00 UTC | Z43: 92 | AA43: 19 | AB43: small (<100 m) | AE43: North Sea & English Channel | AG43: 0 | AH43: 0 | AI43: 0
A44: 244022940 | B44: YE 117 DEN BREEEN | C44: Netherlands | D44: fishing | F44: 0 | G44: PH8814 | H44: 51.66579 | I44: 4.09564 | J44: moving | K44: idle | L44: 0 | M44: 228.7 | N44: 0 | O44: 0 | P44: 0 | Q44: FISHING GROUND | R44: FISHING GROUND | S44: other_text | Z44: 20 | AA44: 9 | AB44: small (<100 m) | AE44: North Sea & English Channel | AG44: 0 | AH44: 1 | AI44: 0
A45: 244002987 | B45: ROMEO | C45: Netherlands | D45: passenger | F45: 0 | G45: PH4751 | H45: 52.36718 | I45: 4.88442 | J45: moving | K45: idle | L45: 0 | N45: 0 | O45: 0 | P45: 0 | S45: missing | Z45: 10 | AA45: 3 | AB45: small (<100 m) | AC45: Amsterdam | AD45: Benelux coast | AE45: North Sea & English Channel | AF45: 5.695129 | AG45: 0 | AH45: 1 | AI45: 0
A46: 244750310 | B46: MADJOE | C46: Netherlands | D46: cargo | F46: 0 | G46: PD5632 | H46: 52.00697 | I46: 4.69331 | J46: moving | K46: idle | L46: 0 | N46: 0 | O46: 0 | P46: 0 | Q46: WEETNIET | R46: WEETNIET | S46: other_text | W46: 02-27 20:00 UTC | Z46: 68 | AA46: 8 | AB46: small (<100 m) | AE46: North Sea & English Channel | AG46: 0 | AH46: 1 | AI46: 0
A47: 244710560 | B47: VOLHARDING | C47: Netherlands | D47: cargo | F47: 0 | G47: PD4749 | H47: 51.69586 | I47: 4.42221 | J47: moving | K47: idle | L47: 0 | N47: 0 | O47: 0 | P47: 0 | Q47: GENEMUIDEN | R47: GENEMUIDEN | S47: other_text | W47: 10-13 09:00 UTC | Z47: 85 | AA47: 9 | AB47: small (<100 m) | AE47: North Sea & English Channel | AG47: 0 | AH47: 1 | AI47: 0
A48: 244710298 | B48: FLOOR VAN AEMSTEL | C48: Netherlands | D48: passenger | F48: 0 | H48: 52.37328 | I48: 4.91109 | J48: moving | K48: idle | L48: 0 | N48: 0 | O48: 0 | P48: 0 | Q48: <.)%4 "%3#()+"!!2> | R48: .)%4 "%3#()+"!!2 | S48: junk | W48: 06-19 16:00 UTC | Z48: 39 | AA48: 7 | AB48: small (<100 m) | AC48: Amsterdam | AD48: Benelux coast | AE48: North Sea & English Channel | AF48: 6.8588133 | AG48: 0 | AH48: 1 | AI48: 0
A49: 244670326 | B49: TS31 INTERNOS | C49: Netherlands | D49: other | F49: 0 | G49: PC6732 | H49: 53.40951 | I49: 6.20495 | J49: moving | K49: idle | L49: 0 | N49: 0 | O49: 0 | P49: 0 | Q49: DENOEVER | R49: DENOEVER | S49: other_text | W49: 06-20 18:00 UTC | Z49: 36 | AA49: 5 | AB49: small (<100 m) | AE49: North Sea & English Channel | AG49: 0 | AH49: 1 | AI49: 0
A50: 244850807 | B50: CHELSEY | C50: Netherlands | D50: other | F50: 0 | G50: PI3071 | H50: 52.42049 | I50: 4.85121 | J50: moving | K50: idle | L50: 0 | M50: 237.6 | N50: 0 | O50: 0 | P50: 0 | S50: missing | Z50: 34 | AA50: 4 | AB50: small (<100 m) | AC50: Amsterdam | AD50: Benelux coast | AE50: North Sea & English Channel | AF50: 3.1100719 | AG50: 0 | AH50: 1 | AI50: 0
A51: 244617076 | B51: ESPERANCE | C51: Netherlands | D51: other | F51: 0 | G51: PF8635 | H51: 52.99006 | I51: 5.88071 | J51: moving | K51: idle | L51: 0 | N51: 0 | O51: 0 | P51: 0 | Q51: UT EN THUS | R51: UT EN THUS | S51: other_text | Z51: 19 | AA51: 5 | AB51: small (<100 m) | AE51: North Sea & English Channel | AG51: 0 | AH51: 1 | AI51: 0
A52: 244780636 | B52: PRINSES C. AMALIA | C52: Netherlands | D52: passenger | F52: 0 | G52: PG5137 | H52: 52.36515 | I52: 4.89302 | J52: moving | K52: moving | L52: 4 | M52: 282.4 | N52: 0 | O52: 0 | P52: 0 | Q52: AMSTERDAM | R52: AMSTERDAM | S52: hub_name | T52: Amsterdam | U52: Amsterdam | V52: AMSTERDAM | Z52: 18 | AA52: 4 | AB52: small (<100 m) | AC52: Amsterdam | AD52: Benelux coast | AE52: North Sea & English Channel | AF52: 6.2911675 | AG52: 0 | AH52: 0 | AI52: 0
A53: 244870322 | B53: ASSISTENT | C53: Netherlands | D53: pleasure | F53: 0 | G53: PD8745 | H53: 51.83536 | I53: 5.49435 | J53: anchored-port | K53: at_berth | L53: 0 | N53: 0 | O53: 0 | P53: 0 | Q53: ALPHEN | R53: ALPHEN | S53: other_text | Z53: 17 | AA53: 5 | AB53: small (<100 m) | AE53: North Sea & English Channel | AG53: 0 | AH53: 0 | AI53: 0
A54: 244770331 | B54: DE RIJKSWATERSTAAT 1 | C54: Netherlands | D54: passenger | F54: 0 | G54: PF2403 | H54: 52.38248 | I54: 4.96008 | J54: moving | K54: idle | L54: 0 | M54: 45 | N54: 0 | O54: 0 | P54: 0 | Q54: NEDERLAND | R54: NEDERLAND | S54: other_text | W54: 02-03 12:00 UTC | AB54: unknown size | AC54: Amsterdam | AD54: Benelux coast | AE54: North Sea & English Channel | AF54: 9.7032101 | AG54: 0 | AH54: 1 | AI54: 0
A55: 235083344 | B55: WINDCAT 25 | C55: United Kingdom | D55: other | F55: 0 | G55: 2DZY5 | H55: 52.45834 | I55: 4.59297 | J55: moving | K55: idle | L55: 0 | N55: 0 | O55: 0 | P55: 0 | Q55: NL-IJM | R55: NL-IJM | S55: other_text | W55: 09-27 11:30 UTC | Z55: 22 | AA55: 6 | AB55: small (<100 m) | AC55: IJmuiden | AD55: Benelux coast | AE55: North Sea & English Channel | AF55: 0.89794746 | AG55: 0 | AH55: 1 | AI55: 0
A56: 244750613 | B56: WINDEKIND | C56: Netherlands | D56: pleasure | F56: 0 | G56: PG5570 | H56: 53.14823 | I56: 5.90585 | J56: anchored-port | K56: at_berth | L56: 0 | N56: 0 | O56: 0 | P56: 0 | Q56: WARTE@@B@@H@$0@A@@H | R56: WARTE@@B@@H@$0@A@@H | S56: other_text | Z56: 27 | AA56: 4 | AB56: small (<100 m) | AE56: North Sea & English Channel | AG56: 0 | AH56: 0 | AI56: 0
A57: 228457800 | B57: ACTI'VENT | C57: France | D57: other | E57: 9985112 | F57: 1 | G57: FMYJ | H57: 49.76213 | I57: 0.37043 | J57: moving | K57: idle | L57: 0.1 | M57: 161.4 | N57: 0 | O57: 0 | P57: 0 | Q57: FECAMP-OWF-FECAMP | R57: FECAMP-OWF-FECAMP | S57: other_text | U57: FECAMP | V57: FECAMP | W57: 10-11 18:30 UTC | X57: FECAMP | Y57: 2026-10-11T07:18:11.971276+00:00 | Z57: 28 | AA57: 9 | AB57: small (<100 m) | AE57: North Sea & English Channel | AG57: 0 | AH57: 1 | AI57: 0
A58: 244700852 | B58: ANTJE | C58: Netherlands | D58: cargo | F58: 0 | G58: PE3769 | H58: 52.61569 | I58: 5.85125 | J58: moving | K58: idle | L58: 0 | N58: 0 | O58: 0 | P58: 0 | Q58: ENKHUIZEN | R58: ENKHUIZEN | S58: other_text | Z58: 79 | AA58: 9 | AB58: small (<100 m) | AE58: North Sea & English Channel | AG58: 0 | AH58: 1 | AI58: 0
A59: 244010913 | B59: ALPHEN | C59: Netherlands | D59: passenger | F59: 0 | G59: PA2779 | H59: 51.83019 | I59: 5.49689 | J59: moving | K59: moving | L59: 2.2 | M59: 190.9 | N59: 0 | O59: 0 | P59: 0 | Q59: ALPHEN | R59: ALPHEN | S59: other_text | Z59: 36 | AA59: 18 | AB59: small (<100 m) | AE59: North Sea & English Channel | AG59: 0 | AH59: 0 | AI59: 0
A60: 244090000 | B60: SEMPER FIDELIS ZK-16 | C60: Netherlands | D60: fishing | F60: 0 | G60: PBGL | H60: 53.33043 | I60: 6.93191 | J60: moving | K60: idle | L60: 0 | M60: 37 | N60: 0 | O60: 0 | P60: 0 | Q60: FISHING GROUNDS | R60: FISHING GROUNDS | S60: other_text | Z60: 24 | AA60: 6 | AB60: small (<100 m) | AC60: Eemshaven | AD60: German Bight & Ems | AE60: North Sea & English Channel | AF60: 14.625976 | AG60: 0 | AH60: 1 | AI60: 0
A61: 255893000 | B61: HEINRICH ESSBERGER | C61: Portugal | D61: tanker | E61: 9939814 | F61: 1 | G61: CQWZ | H61: 50.76775 | I61: -1.2465 | J61: moving | K61: moving | L61: 10.3 | M61: 285.5 | N61: 0 | O61: 0 | P61: 0 | Q61: HAMBLE | R61: HAMBLE | S61: other_text | W61: 10-11 04:00 UTC | Z61: 119 | AA61: 18 | AB61: medium (100-200 m) | AC61: Southampton | AD61: Dover Strait & Channel | AE61: North Sea & English Channel | AF61: 18.233482 | AG61: 0 | AH61: 0 | AI61: 0
A62: 245779000 | B62: WATERPOORT | C62: Netherlands | D62: tug | F62: 0 | G62: PD2884 | H62: 53.17371 | I62: 6.70565 | J62: moving | K62: idle | L62: 0 | M62: 0 | N62: 0 | O62: 0 | P62: 0 | Q62: DELFZIJL | R62: DELFZIJL | S62: other_text | U62: DELFZIJL | V62: DELFZIJL | W62: 12-08 16:00 UTC | Z62: 21 | AA62: 6 | AB62: small (<100 m) | AE62: North Sea & English Channel | AG62: 0 | AH62: 1 | AI62: 0
A63: 244373705 | B63: LARGO | C63: Netherlands | D63: pleasure | F63: 0 | G63: PC7863 | H63: 51.89511 | I63: 4.21797 | J63: moving | K63: idle | L63: 0 | N63: 0 | O63: 0 | P63: 0 | Q63: BRIELLE . | R63: BRIELLE . | S63: other_text | W63: 05-01 19:00 UTC | Z63: 23 | AA63: 5 | AB63: small (<100 m) | AC63: Rotterdam | AD63: Benelux coast | AE63: North Sea & English Channel | AF63: 10.134151 | AG63: 0 | AH63: 1 | AI63: 0
A64: 244780658 | B64: SAEFTINGHE | C64: Netherlands | D64: pleasure | F64: 0 | G64: PA3425 | H64: 51.90722 | I64: 4.34497 | J64: anchored-sea | K64: at_anchor | L64: 0 | M64: 0 | N64: 0 | O64: 0 | P64: 0 | Q64: VLAARDINGEN | R64: VLAARDINGEN | S64: other_text | U64: VLAARDINGEN | V64: VLAARDINGEN | Z64: 24 | AA64: 5 | AB64: small (<100 m) | AC64: Rotterdam | AD64: Benelux coast | AE64: North Sea & English Channel | AF64: 17.4576 | AG64: 0 | AH64: 0 | AI64: 0
A65: 244690812 | B65: GRIETJE | C65: Netherlands | D65: passenger | F65: 0 | G65: PI3118 | H65: 52.51723 | I65: 5.4379 | J65: moving | K65: idle | L65: 0 | M65: 0 | N65: 0 | O65: 0 | P65: 0 | Q65: YSSELMEER/WADDEN | R65: YSSELMEER/WADDEN | S65: other_text | W65: 08-18 14:55 UTC | Z65: 42 | AA65: 6 | AB65: small (<100 m) | AE65: North Sea & English Channel | AG65: 0 | AH65: 1 | AI65: 0
A66: 244660378 | B66: FRIESLAND | C66: Netherlands | D66: passenger | F66: 0 | G66: PH4142 | H66: 52.69887 | I66: 5.29017 | J66: anchored-sea | K66: at_anchor | L66: 0.1 | M66: 278.6 | N66: 0 | O66: 0 | P66: 0 | Q66: ENKHUIZEN<>MEDEMBLIK | R66: MEDEMBLIK | S66: other_text | Z66: 53 | AA66: 10 | AB66: small (<100 m) | AE66: North Sea & English Channel | AG66: 0 | AH66: 0 | AI66: 0
A67: 244660614 | B67: COTRANS 1 | C67: Netherlands | D67: cargo | F67: 0 | G67: PF4317 | H67: 51.90248 | I67: 5.53403 | J67: moving | K67: idle | L67: 0 | N67: 0 | O67: 0 | P67: 0 | Q67: IJZENDOORN HAVEN TE | R67: IJZENDOORN HAVEN TE | S67: other_text | W67: 10-09 14:52 UTC | Z67: 80 | AA67: 10 | AB67: small (<100 m) | AE67: North Sea & English Channel | AG67: 0 | AH67: 1 | AI67: 0
A68: 244710836 | B68: WILHELMUS | C68: Netherlands | D68: passenger | F68: 0 | G68: PD6192 | H68: 52.35437 | I68: 4.88689 | J68: moving | K68: idle | L68: 0 | N68: 0 | O68: 0 | P68: 0 | Q68: ADAM | R68: ADAM | S68: other_text | W68: 01-01 00:00 UTC | Z68: 18 | AA68: 5 | AB68: small (<100 m) | AC68: Amsterdam | AD68: Benelux coast | AE68: North Sea & English Channel | AF68: 6.8088154 | AG68: 0 | AH68: 1 | AI68: 0
A69: 244780873 | B69: DEO JUVANTE | C69: Netherlands | D69: pleasure | F69: 0 | G69: PF2300 | H69: 53.1757 | I69: 5.42162 | J69: anchored-sea | K69: at_anchor | L69: 0 | M69: 0 | N69: 0 | O69: 0 | P69: 0 | S69: missing | Z69: 26 | AA69: 5 | AB69: small (<100 m) | AE69: North Sea & English Channel | AG69: 0 | AH69: 0 | AI69: 0
A70: 244710820 | B70: FESTINA LENTE @B | C70: Netherlands | D70: other | F70: 0 | G70: PH7999 | H70: 51.91616 | I70: 4.48495 | J70: moving | K70: idle | L70: 0 | M70: 298.7 | N70: 0 | O70: 0 | P70: 0 | Q70: @@@@@@@@@@@@@@B@@@A | R70: @@@@@@@@@@@@@@B@@@A | S70: other_text | Z70: 23 | AA70: 4 | AB70: small (<100 m) | AC70: Rotterdam | AD70: Benelux coast | AE70: North Sea & English Channel | AF70: 26.659345 | AG70: 0 | AH70: 1 | AI70: 0
A71: 244780747 | B71: PATRICK | C71: Netherlands | D71: other | F71: 0 | G71: PD8674 | H71: 51.57438 | I71: 5.10681 | J71: moving | K71: idle | L71: 0.1 | N71: 0 | O71: 0 | P71: 0 | Q71: TILBURG | R71: TILBURG | S71: other_text | Z71: 50 | AA71: 7 | AB71: small (<100 m) | AE71: North Sea & English Channel | AG71: 0 | AH71: 1 | AI71: 0
A72: 244730008 | B72: BRUINVIS | C72: Netherlands | D72: passenger | F72: 0 | G72: PF4072 | H72: 53.40918 | I72: 6.20385 | J72: moving | K72: idle | L72: 0 | N72: 0 | O72: 0 | P72: 0 | Q72: DOLLARD | R72: DOLLARD | S72: other_text | W72: 09-07 12:00 UTC | Z72: 42 | AA72: 10 | AB72: small (<100 m) | AE72: North Sea & English Channel | AG72: 0 | AH72: 1 | AI72: 0
A73: 232031183 | B73: HENDRIKA JACOBA | C73: United Kingdom | D73: fishing | E73: 9877389 | F73: 1 | G73: MIHQ9 | H73: 51.44417 | I73: 3.59012 | J73: moving | K73: idle | L73: 0 | M73: 22 | N73: 0 | O73: 0 | P73: 0 | Q73: FISHING GROUNDS | R73: FISHING GROUNDS | S73: other_text | W73: 09-05 02:00 UTC | Z73: 25 | AA73: 9 | AB73: small (<100 m) | AC73: Vlissingen | AD73: Benelux coast | AE73: North Sea & English Channel | AF73: 0.84081333 | AG73: 0 | AH73: 1 | AI73: 0
A74: 244650118 | B74: DANKBAARHEID | C74: Netherlands | D74: pleasure | F74: 0 | G74: PD5423 | H74: 52.95806 | I74: 4.76962 | J74: anchored-sea | K74: at_anchor | L74: 0 | M74: 0 | N74: 0 | O74: 0 | P74: 0 | Q74: DEN HELDER | R74: DEN HELDER | S74: other_text | U74: DEN HELDER | V74: DEN HELDER | W74: 10-16 12:00 UTC | Z74: 24 | AA74: 5 | AB74: small (<100 m) | AE74: North Sea & English Channel | AG74: 0 | AH74: 0 | AI74: 0
A75: 244191102 | B75: FAYE | C75: Netherlands | D75: cargo | F75: 0 | G75: PF3706 | H75: 51.90224 | I75: 5.54488 | J75: moving | K75: moving | L75: 0.8 | M75: 206.2 | N75: 0 | O75: 0 | P75: 0 | Q75: MAASVLAKTE | R75: MAASVLAKTE | S75: hub_name | T75: Rotterdam | U75: Rotterdam | W75: 10-03 01:00 UTC | Z75: 135 | AA75: 15 | AB75: medium (100-200 m) | AE75: North Sea & English Channel | AG75: 0 | AH75: 0 | AI75: 0
A76: 205482190 | B76: NORDICA | C76: Belgium | D76: cargo | F76: 0 | G76: OT4821 | H76: 51.7615 | I76: 5.74316 | J76: moving | K76: moving | L76: 6.5 | M76: 163.1 | N76: 0 | O76: 0 | P76: 0 | Q76: GENNEP | R76: GENNEP | S76: other_text | W76: 10-10 15:13 UTC | Z76: 110 | AA76: 12 | AB76: medium (100-200 m) | AE76: North Sea & English Channel | AG76: 0 | AH76: 0 | AI76: 0
A77: 311001790 | B77: MISJE SAKURA | C77: Bahamas | D77: cargo | E77: 1049742 | F77: 1 | G77: C6IW3 | H77: 51.93349 | I77: 4.05181 | J77: moving | K77: idle | L77: 0 | M77: 104.8 | N77: 0 | O77: 0 | P77: 0 | Q77: ROTTERDAM | R77: ROTTERDAM | S77: hub_name | T77: Rotterdam | U77: Rotterdam | V77: ROTTERDAM | W77: 10-06 16:00 UTC | Z77: 90 | AA77: 16 | AB77: small (<100 m) | AC77: Rotterdam | AD77: Benelux coast | AE77: North Sea & English Channel | AF77: 3.7791689 | AG77: 0 | AH77: 1 | AI77: 0
A78: 244184488 | B78: IJVEER 65 | C78: Netherlands | D78: passenger | F78: 0 | G78: PC7736 | H78: 52.3975 | I78: 4.8889 | J78: moving | K78: moving | L78: 9.3 | M78: 165.2 | N78: 0 | O78: 0 | P78: 0 | Q78: AMSTERDAM | R78: AMSTERDAM | S78: hub_name | T78: Amsterdam | U78: Amsterdam | V78: AMSTERDAM | W78: 11-03 10:00 UTC | AB78: unknown size | AC78: Amsterdam | AD78: Benelux coast | AE78: North Sea & English Channel | AF78: 4.6829207 | AG78: 0 | AH78: 0 | AI78: 0
A79: 244690930 | B79: VEERMAN VAN KAMPEN | C79: Netherlands | D79: passenger | F79: 0 | G79: PH6484 | H79: 52.56129 | I79: 5.9151 | J79: moving | K79: idle | L79: 0 | M79: 0 | N79: 0 | O79: 0 | P79: 0 | Q79: KAMPEN>; | R79: ; | S79: junk | W79: 07-27 16:30 UTC | Z79: 45 | AA79: 6 | AB79: small (<100 m) | AE79: North Sea & English Channel | AG79: 0 | AH79: 1 | AI79: 0
A80: 244670846 | B80: RIGEL | C80: Netherlands | D80: cargo | F80: 0 | G80: PD2143 | H80: 51.96025 | I80: 5.65593 | J80: moving | K80: idle | L80: 0 | M80: 0 | N80: 0 | O80: 0 | P80: 0 | S80: missing | W80: 11-24 12:00 UTC | Z80: 80 | AA80: 8 | AB80: small (<100 m) | AE80: North Sea & English Channel | AG80: 0 | AH80: 1 | AI80: 0
A81: 244004304 | B81: BR-37 (VICTOR) | C81: Netherlands | D81: fishing | F81: 0 | G81: PA6742 | H81: 51.39572 | I81: 3.56538 | J81: anchored-sea | K81: at_anchor | L81: 0.1 | N81: 0 | O81: 0 | P81: 0 | S81: missing | Z81: 18 | AA81: 4 | AB81: small (<100 m) | AC81: Vlissingen | AD81: Benelux coast | AE81: North Sea & English Channel | AF81: 5.0270117 | AG81: 0 | AH81: 0 | AI81: 0
A82: 205595190 | B82: BARENDSZ | C82: Belgium | D82: cargo | E82: 232498 | F82: 0 | G82: PD4821 | H82: 51.86854 | I82: 4.25335 | J82: moving | K82: moving | L82: 5.7 | M82: 117.8 | N82: 0 | O82: 0 | P82: 0 | S82: missing | W82: 11-11 12:41 UTC | X82: EUROPOORT | Y82: 2026-10-11T06:34:22.855876+00:00 | Z82: 86 | AA82: 11 | AB82: small (<100 m) | AC82: Rotterdam | AD82: Benelux coast | AE82: North Sea & English Channel | AF82: 13.881775 | AG82: 0 | AH82: 0 | AI82: 0
A83: 244377391 | B83: STOLT LUDWIGSHAFEN | C83: Netherlands | D83: tanker | F83: 0 | G83: PB3517 | H83: 50.99608 | I83: 6.96201 | J83: moving | K83: moving | L83: 7.8 | M83: 345.6 | N83: 0 | O83: 0 | P83: 0 | Q83: ANTWERPEN KANAALDOK | R83: ANTWERPEN KANAALDOK | S83: hub_name | T83: Antwerp | U83: Antwerp | V83: ANTWERPEN | W83: 10-12 23:35 UTC | Z83: 135 | AA83: 18 | AB83: medium (100-200 m) | AE83: North Sea & English Channel | AG83: 0 | AH83: 0 | AI83: 0
A84: 244670362 | B84: UQ15 CAROLINE ELISE | C84: Netherlands | D84: fishing | F84: 0 | G84: PBEA | H84: 53.44455 | I84: 6.82598 | J84: moving | K84: idle | L84: 0.1 | N84: 0 | O84: 0 | P84: 0 | Q84: EEMSHAVEN | R84: EEMSHAVEN | S84: hub_name | T84: Eemshaven | U84: Eemshaven | V84: EEMSHAVEN | Z84: 20 | AA84: 6 | AB84: small (<100 m) | AC84: Eemshaven | AD84: German Bight & Ems | AE84: North Sea & English Channel | AF84: 1.1087291 | AG84: 0 | AH84: 1 | AI84: 0
A85: 244780317 | B85: BREITNER | C85: Netherlands | D85: passenger | F85: 0 | G85: PD2104 | H85: 52.37708 | I85: 4.90011 | J85: moving | K85: idle | L85: 0 | M85: 0 | N85: 0 | O85: 0 | P85: 0 | Q85: AMSTERDAM | R85: AMSTERDAM | S85: hub_name | T85: Amsterdam | U85: Amsterdam | V85: AMSTERDAM | Z85: 19 | AA85: 4 | AB85: small (<100 m) | AC85: Amsterdam | AD85: Benelux coast | AE85: North Sea & English Channel | AF85: 6.0042226 | AG85: 0 | AH85: 1 | AI85: 0
A86: 244730368 | B86: CONNEMARA | C86: Netherlands | D86: tanker | F86: 0 | G86: PB9419 | H86: 52.39668 | I86: 4.89112 | J86: moving | K86: moving | L86: 1.2 | M86: 334.8 | N86: 0 | O86: 0 | P86: 0 | Q86: AMSTERDAM AFRIKAHAVE | R86: AMSTERDAM AFRIKAHAVE | S86: hub_name | T86: Amsterdam | U86: Amsterdam | V86: AMSTERDAM | W86: 10-10 16:03 UTC | X86: AMSTERDAM | Y86: 2026-10-11T07:32:54.233135+00:00 | Z86: 110 | AA86: 12 | AB86: medium (100-200 m) | AC86: Amsterdam | AD86: Benelux coast | AE86: North Sea & English Channel | AF86: 4.8394289 | AG86: 0 | AH86: 0 | AI86: 0
A87: 244670578 | B87: LAUWERSZEE | C87: Netherlands | D87: passenger | F87: 0 | G87: PI2621 | H87: 53.17378 | I87: 5.4109 | J87: moving | K87: idle | L87: 0 | N87: 0 | O87: 0 | P87: 0 | S87: missing | Z87: 26 | AA87: 6 | AB87: small (<100 m) | AE87: North Sea & English Channel | AG87: 0 | AH87: 1 | AI87: 0
A88: 244830719 | B88: BEAU | C88: Netherlands | D88: passenger | F88: 0 | G88: PI8272 | H88: 52.38848 | I88: 4.88974 | J88: moving | K88: idle | L88: 0 | N88: 0 | O88: 0 | P88: 0 | Q88: AMSTERDAM | R88: AMSTERDAM | S88: hub_name | T88: Amsterdam | U88: Amsterdam | V88: AMSTERDAM | Z88: 10 | AA88: 3 | AB88: small (<100 m) | AC88: Amsterdam | AD88: Benelux coast | AE88: North Sea & English Channel | AF88: 4.9024486 | AG88: 0 | AH88: 1 | AI88: 0
A89: 244740095 | B89: KARST | C89: Netherlands | D89: other | F89: 0 | G89: PC3323 | H89: 52.77312 | I89: 5.03779 | J89: moving | K89: idle | L89: 0 | N89: 0 | O89: 0 | P89: 0 | Q89: MIDDENMEER | R89: MIDDENMEER | S89: other_text | W89: 12-16 07:24 UTC | Z89: 35 | AA89: 6 | AB89: small (<100 m) | AE89: North Sea & English Channel | AG89: 0 | AH89: 1 | AI89: 0
A90: 244660065 | B90: ANDA | C90: Netherlands | D90: cargo | F90: 0 | G90: PB4448 | H90: 51.88744 | I90: 5.45332 | J90: moving | K90: moving | L90: 7.1 | M90: 240.9 | N90: 0 | O90: 0 | P90: 0 | Q90: STABROEK | R90: STABROEK | S90: other_text | W90: 10-11 09:04 UTC | Z90: 135 | AA90: 23 | AB90: medium (100-200 m) | AE90: North Sea & English Channel | AG90: 0 | AH90: 0 | AI90: 0
A91: 244924000 | B91: VB HUDSON | C91: Netherlands | D91: tug | E91: 9402421 | F91: 1 | G91: PFJC | H91: 51.89938 | I91: 4.39737 | J91: moving | K91: idle | L91: 0.2 | M91: 330 | N91: 0 | O91: 0 | P91: 0 | Q91: ROTTERDAM | R91: ROTTERDAM | S91: hub_name | T91: Rotterdam | U91: Rotterdam | V91: ROTTERDAM | W91: 07-04 20:00 UTC | Z91: 28 | AA91: 10 | AB91: small (<100 m) | AC91: Rotterdam | AD91: Benelux coast | AE91: North Sea & English Channel | AF91: 21.154306 | AG91: 0 | AH91: 1 | AI91: 0
A92: 235102528 | B92: BSC VOLUNTEER | C92: United Kingdom | D92: official | E92: 835461500 | F92: 0 | G92: 2HCP6 | H92: 51.32952 | I92: 1.42274 | J92: anchored-port | K92: at_berth | L92: 0 | M92: 270.9 | N92: 0 | O92: 0 | P92: 0 | Q92: RAMSGATE | R92: RAMSGATE | S92: other_text | U92: RAMSGATE | V92: RAMSGATE | W92: 10-09 08:00 UTC | Z92: 24 | AA92: 8 | AB92: small (<100 m) | AE92: North Sea & English Channel | AG92: 0 | AH92: 0 | AI92: 0
A93: 211440330 | B93: THOMAS DEYMANN 1-2 | C93: Germany | D93: cargo | F93: 0 | G93: DH5589 | H93: 51.88243 | I93: 5.756 | J93: moving | K93: moving | L93: 5.6 | M93: 112.9 | N93: 0 | O93: 0 | P93: 0 | Q93: HASSELT | R93: HASSELT | S93: other_text | W93: 10-12 23:51 UTC | X93: EUROPOORT | Y93: 2026-10-10T23:03:37.173106+00:00 | Z93: 172 | AA93: 12 | AB93: medium (100-200 m) | AE93: North Sea & English Channel | AG93: 0 | AH93: 0 | AI93: 0
A94: 244650312 | B94: AMAZONE | C94: Netherlands | D94: other | F94: 0 | G94: PB3216 | H94: 51.81569 | I94: 4.78658 | J94: moving | K94: moving | L94: 9 | M94: 259.7 | N94: 0 | O94: 0 | P94: 0 | Q94: EEMHAVEN | R94: EEMHAVEN | S94: other_text | W94: 10-11 08:00 UTC | X94: DORDRECHT | Y94: 2026-10-05T13:31:48.941444+00:00 | Z94: 135 | AA94: 15 | AB94: medium (100-200 m) | AE94: North Sea & English Channel | AG94: 0 | AH94: 0 | AI94: 0
A95: 244740497 | B95: ANORA | C95: Netherlands | D95: cargo | F95: 0 | G95: PF8500 | H95: 51.13759 | I95: 3.33213 | J95: moving | K95: idle | L95: 0 | N95: 0 | O95: 0 | P95: 0 | S95: missing | Z95: 55 | AA95: 8 | AB95: small (<100 m) | AE95: North Sea & English Channel | AG95: 0 | AH95: 1 | AI95: 0
A96: 244849000 | B96: KRAKESANDT | C96: Netherlands | D96: other | E96: 9823807 | F96: 1 | G96: PELG | H96: 51.61689 | I96: 3.30642 | J96: anchored-sea | K96: at_anchor | L96: 1.7 | M96: 30.5 | N96: 0 | O96: 0 | P96: 0 | Q96: THORNTONBANK | R96: THORNTONBANK | S96: other_text | W96: 10-11 11:00 UTC | X96: HANSWEERT | Y96: 2026-10-11T01:53:25.391227+00:00 | Z96: 106 | AA96: 16 | AB96: medium (100-200 m) | AE96: North Sea & English Channel | AG96: 0 | AH96: 0 | AI96: 0
A97: 244717904 | B97: APOTHEOSE | C97: Netherlands | D97: cargo | F97: 0 | G97: PG9313 | H97: 51.35024 | I97: 3.85918 | J97: moving | K97: moving | L97: 6.6 | M97: 252.7 | N97: 0 | O97: 0 | P97: 0 | Q97: ANTWERPEN | R97: ANTWERPEN | S97: hub_name | T97: Antwerp | U97: Antwerp | V97: ANTWERPEN | W97: 09-18 09:21 UTC | X97: ANTWERPEN | Y97: 2026-10-11T05:56:12.516783+00:00 | Z97: 196 | AA97: 24 | AB97: medium (100-200 m) | AC97: Terneuzen | AD97: Benelux coast | AE97: North Sea & English Channel | AF97: 3.0287967 | AG97: 0 | AH97: 0 | AI97: 0
A98: 205268790 | B98: AVALONA | C98: Belgium | D98: cargo | F98: 0 | G98: OT2687 | H98: 51.22917 | I98: 3.22271 | J98: anchored-port | K98: at_berth | L98: 0 | N98: 0 | O98: 0 | P98: 0 | Q98: BRUGGE KLEIN HANDEL | R98: BRUGGE KLEIN HANDEL | S98: other_text | Z98: 85 | AA98: 10 | AB98: small (<100 m) | AC98: Zeebrugge | AD98: Benelux coast | AE98: North Sea & English Channel | AF98: 12.424548 | AG98: 0 | AH98: 0 | AI98: 0
A99: 209168000 | B99: AGATH | C99: Cyprus | D99: tanker | E99: 9537642 | F99: 1 | G99: 5BFJ6 | H99: 51.89376 | I99: 4.44534 | J99: anchored-sea | K99: at_anchor | L99: 0.1 | M99: 199.6 | N99: 0 | O99: 0 | P99: 0 | Q99: NL RTM | R99: NL RTM | S99: locode | T99: Rotterdam | U99: Rotterdam | W99: 10-08 08:00 UTC | Z99: 121 | AA99: 16 | AB99: medium (100-200 m) | AC99: Rotterdam | AD99: Benelux coast | AE99: North Sea & English Channel | AF99: 24.494423 | AG99: 0 | AH99: 0 | AI99: 0
A100: 304914000 | B100: BALTIC BLUE | C100: Antigua and Barbuda | D100: cargo | E100: 9131589 | F100: 1 | G100: V2IH7 | H100: 53.09785 | I100: 7.36935 | J100: anchored-port | K100: at_berth | L100: 0 | M100: 230.9 | N100: 0 | O100: 0 | P100: 0 | Q100: DE PAP | R100: DE PAP | S100: locode_other | W100: 07-18 09:00 UTC | Z100: 88 | AA100: 14 | AB100: small (<100 m) | AE100: North Sea & English Channel | AG100: 0 | AH100: 0 | AI100: 0
...
